rail/hub/__init__.py
rail/hub/_version.py
rail/hub/commands.py
rail/hub/options.py
rail/hub/scripts.py
pz_rail_hub-0.1.2.dist-info/LICENSE
pz_rail_hub-0.1.2.dist-info/METADATA
pz_rail_hub-0.1.2.dist-info/WHEEL
pz_rail_hub-0.1.2.dist-info/entry_points.txt
pz_rail_hub-0.1.2.dist-info/top_level.txt
pz_rail_hub-0.1.2.dist-info/RECORD
