Metadata-Version: 2.1
Name: pz-rail-hub
Version: 0.1.2
Author-email: "LSST Dark Energy Science Collaboration (DESC)" <later@later.com>
License: MIT License
Classifier: Development Status :: 4 - Beta
Classifier: License :: OSI Approved :: MIT License
Classifier: Intended Audience :: Developers
Classifier: Intended Audience :: Science/Research
Classifier: Operating System :: OS Independent
Classifier: Programming Language :: Python
License-File: LICENSE
Requires-Dist: pz-rail-base
Requires-Dist: click
Requires-Dist: pyaml
Provides-Extra: algos
Requires-Dist: pz-rail-pipelines[full] ; extra == 'algos'
Provides-Extra: dev
Requires-Dist: pz-rail-pipelines[full] ; extra == 'dev'
Requires-Dist: jupyter ; extra == 'dev'
Requires-Dist: seaborn ; extra == 'dev'
Requires-Dist: coverage ; extra == 'dev'
Requires-Dist: pytest ; extra == 'dev'
Requires-Dist: pytest-cov ; extra == 'dev'
Requires-Dist: pre-commit ; extra == 'dev'
Requires-Dist: pylint ; extra == 'dev'
Provides-Extra: docs
Requires-Dist: nbsphinx ; extra == 'docs'
Requires-Dist: sphinx (==6.1.3) ; extra == 'docs'
Requires-Dist: sphinx-rtd-theme (==1.2.0) ; extra == 'docs'
Requires-Dist: sphinx-autoapi (==2.0.1) ; extra == 'docs'
Provides-Extra: nb
Requires-Dist: pz-rail-pipelines[full] ; extra == 'nb'
Requires-Dist: jupyter ; extra == 'nb'
Requires-Dist: seaborn ; extra == 'nb'
